toru/__init__.py
toru-0.4.0.dist-info/METADATA
toru-0.4.0.dist-info/WHEEL
toru-0.4.0.dist-info/top_level.txt
toru-0.4.0.dist-info/RECORD
